{
  "project_info": {
    "project_number": "196824820371",
    "firebase_url": "https://myjokes-a3279.firebaseio.com",
    "project_id": "myjokes-a3279",
    "storage_bucket": "myjokes-a3279.appspot.com"
  },
  "client": [
    {
      "client_info": {
        "mobilesdk_app_id": "1:196824820371:android:df9c98d2a75d4a2dac7b66",
        "android_client_info": {
          "package_name": "com.arose.myjokes"
        }
      },
      "oauth_client": [
        {
          "client_id": "196824820371-msk7tcbbvabua2gn9goi4mq02t4djs7d.apps.googleusercontent.com",
          "client_type": 1,
          "android_info": {
            "package_name": "com.arose.myjokes",
            "certificate_hash": "baffc88fcdd3feac14cd09440f8a898c04fb5259"
          }
        },
        {
          "client_id": "196824820371-d98qr7ntsj4rklcvcb4henovbsc99n5l.apps.googleusercontent.com",
          "client_type": 3
        }
      ],
      "api_key": [
        {
          "current_key": "AIzaSyCfreHAmgFTgT4xuGTusBjpwlrc46HpkY0"
        }
      ],
      "services": {
        "appinvite_service": {
          "other_platform_oauth_client": [
            {
              "client_id": "196824820371-d98qr7ntsj4rklcvcb4henovbsc99n5l.apps.googleusercontent.com",
              "client_type": 3
            }
          ]
        }
      }
    }
  ],
  "configuration_version": "1"
}